[
  {
    "title": "2026-04-27",
    "file": "notes/2026-04-27.md",
    "mod_time": 1777307468.3126247
  },
  {
    "title": "2026-04-23",
    "file": "notes/2026-04-23.md",
    "mod_time": 1776958452.2242079
  },
  {
    "title": "2026-04-21",
    "file": "notes/2026-04-21.md",
    "mod_time": 1776785006.6253934
  },
  {
    "title": "2026-04-17",
    "file": "notes/2026-04-17.md",
    "mod_time": 1776610812.740748
  },
  {
    "title": "2026-04-19",
    "file": "notes/2026-04-19.md",
    "mod_time": 1776610792.6425283
  },
  {
    "title": "2026-04-15",
    "file": "notes/2026-04-15.md",
    "mod_time": 1776262784.5519671
  },
  {
    "title": "2026-04-14",
    "file": "notes/2026-04-14.md",
    "mod_time": 1776172588.2698398
  },
  {
    "title": "2026-04-13",
    "file": "notes/2026-04-13.md",
    "mod_time": 1776091368.1940026
  },
  {
    "title": "2026-04-12",
    "file": "notes/2026-04-12.md",
    "mod_time": 1775999145.4996333
  }
]